Metadata-Version: 2.1
Name: testlyh
Version: 0.0.2
Summary: this is a test
Home-page: https://github.com/
Author: lyh
Author-email: 1271521082@qq.com
License: UNKNOWN
Platform: UNKNOWN
Classifier: Programming Language :: Python :: 3
Classifier: License :: OSI Approved :: MIT License
Classifier: Operating System :: OS Independent
